vulndb/__init__.py
vulndb/db-version.txt
vulndb/db_vuln.py
vulndb/requirements-dev.txt
vulndb/version.txt
vulndb/constants/__init__.py
vulndb/constants/cwe.py
vulndb/constants/owasp.py
vulndb/constants/wasc.py
vulndb/db/en/1-allowed-http-methods.json
vulndb/db/en/10-common-sensitive-file.json
vulndb/db/en/11-cookie-set-for-parent-domain.json
vulndb/db/en/12-credit-card-number-disclosure.json
vulndb/db/en/13-cross-site-request-forgery.json
vulndb/db/en/14-cvs-svn-user-disclosure.json
vulndb/db/en/15-directory-listing.json
vulndb/db/en/16-e-mail-address-disclosure.json
vulndb/db/en/17-file-inclusion.json
vulndb/db/en/18-form-based-file-upload.json
vulndb/db/en/19-missing-strict-transport-security-header.json
vulndb/db/en/2-a-backdoor-file-exists-on-the-server.json
vulndb/db/en/20-misconfiguration-in-limit-directive-of-htaccess-file.json
vulndb/db/en/21-html-object.json
vulndb/db/en/22-httponly-cookie.json
vulndb/db/en/23-publicly-writable-directory.json
vulndb/db/en/24-insecure-client-access-policy.json
vulndb/db/en/25-insecure-cookie.json
vulndb/db/en/26-access-control-allow-origin-star.json
vulndb/db/en/27-insecure-cross-domain-policy-allow-access-from.json
vulndb/db/en/29-interesting-response.json
vulndb/db/en/3-backup-directory.json
vulndb/db/en/30-ldap-injection.json
vulndb/db/en/31-exposed-localstart-asp-page.json
vulndb/db/en/32-mixed-resource.json
vulndb/db/en/33-nosql-injection.json
vulndb/db/en/34-blind-nosql-injection-differential-analysis.json
vulndb/db/en/35-access-restriction-bypass-via-origin-spoof.json
vulndb/db/en/36-operating-system-command-injection.json
vulndb/db/en/38-password-field-with-auto-complete.json
vulndb/db/en/39-path-traversal.json
vulndb/db/en/4-backup-file.json
vulndb/db/en/40-private-ip-address-disclosure.json
vulndb/db/en/41-response-splitting.json
vulndb/db/en/42-remote-file-inclusion.json
vulndb/db/en/43-session-fixation.json
vulndb/db/en/44-source-code-disclosure.json
vulndb/db/en/45-sql-injection.json
vulndb-0.1.3.dist-info/LICENSE
vulndb-0.1.3.dist-info/METADATA
vulndb-0.1.3.dist-info/WHEEL
vulndb-0.1.3.dist-info/top_level.txt
vulndb-0.1.3.dist-info/RECORD
