Metadata-Version: 2.1
Name: vulndb
Version: 0.1.3
Summary: Provides access to the vulndb information
Home-page: https://github.com/vulndb/python-sdk/
Author: Andres Riancho
Author-email: self@andresriancho.com
License: BSD 3-clause
Platform: Linux
Classifier: Development Status :: 5 - Production/Stable
Classifier: Intended Audience :: Developers
Classifier: License :: OSI Approved :: BSD License
Classifier: Natural Language :: English
Classifier: Operating System :: POSIX :: Linux
Classifier: Operating System :: Microsoft :: Windows
Classifier: Programming Language :: Python
Classifier: Programming Language :: Python :: 2.7
Classifier: Programming Language :: Python :: 3
Classifier: Topic :: Security
